stressinjector/__init__.py
stressinjector/cpu.py
stressinjector/helper.py
stressinjector/memory.py
stressinjector/models.py
stressinjector/requirements.txt
stressinjector/url.py
stress_injector-0.9.dist-info/LICENSE
stress_injector-0.9.dist-info/METADATA
stress_injector-0.9.dist-info/WHEEL
stress_injector-0.9.dist-info/top_level.txt
stress_injector-0.9.dist-info/RECORD
