Metadata-Version: 2.1
Name: stress-injector
Version: 0.9
Summary: Python module, to inject memory and CPU stress, and URL load test
Author-email: Vignesh Sivanandha Rao <svignesh1793@gmail.com>
License: MIT License
Project-URL: Homepage, https://github.com/thevickypedia/stress-injector
Project-URL: Docs, https://thevickypedia.github.io/stress-injector/
Project-URL: Source, https://github.com/thevickypedia/stress-injector
Project-URL: Bug Tracker, https://github.com/thevickypedia/stress-injector/issues
Project-URL: Release Notes, https://github.com/thevickypedia/stress-injector/blob/main/release_notes.rst
Keywords: stress-test,numpy-arrays,cpu-stress,memory-stress,url-stress,multiprocessing,multithreading
Classifier: Development Status :: 5 - Production/Stable
Classifier: Intended Audience :: Telecommunications Industry
Classifier: Intended Audience :: Information Technology
Classifier: License :: OSI Approved :: MIT License
Classifier: Operating System :: OS Independent
Classifier: License :: OSI Approved :: MIT License
Classifier: Programming Language :: Python :: 3.8
Classifier: Programming Language :: Python :: 3.9
Classifier: Programming Language :: Python :: 3.10
Classifier: Programming Language :: Python :: 3.11
Requires-Python: >=3.8
License-File: LICENSE
Requires-Dist: numpy >=1.20.0
Requires-Dist: psutil >=5.9.0
Requires-Dist: tqdm >=4.56.0
Requires-Dist: requests
Provides-Extra: dev
Requires-Dist: pre-commit ; extra == 'dev'
